hmtools/__init__.py
hmtools/file/__init__.py
hmtools/file/csv_segment.py
hmtools-0.0.1.dist-info/LICENSE
hmtools-0.0.1.dist-info/METADATA
hmtools-0.0.1.dist-info/WHEEL
hmtools-0.0.1.dist-info/top_level.txt
hmtools-0.0.1.dist-info/RECORD
