Metadata-Version: 2.1
Name: hmtools
Version: 0.0.1
Summary: Some tools for research
Author: AeroH
Author-email: zhang.yuh@outlook.com
Requires-Python: >=3.8
License-File: LICENSE
Requires-Dist: pandas (==1.4.2)
